om_api/___init___.py
om_api/om_api.py
om_api-0.1.22.dist-info/LICENSE
om_api-0.1.22.dist-info/METADATA
om_api-0.1.22.dist-info/WHEEL
om_api-0.1.22.dist-info/top_level.txt
om_api-0.1.22.dist-info/RECORD
