Metadata-Version: 2.1
Name: om-api
Version: 0.1.22
Summary: Functions to work with Optimacros API
Home-page: https://github.com/pahMelnik/om_api
Author: Matvey Scherbakov
Author-email: l89851175735@gmail.com
License: MIT see LICESE file
Classifier: Programming Language :: Python :: 3
Classifier: License :: OSI Approved :: MIT License
Classifier: Operating System :: OS Independent
License-File: LICENSE
Requires-Dist: requests
Requires-Dist: pandas
